AUTHORS
CHANGES
LICENSE
MANIFEST.in
README.rst
setup.py
doc/api.rst
doc/commands.rst
doc/guide.rst
doc/index.rst
wiggelen/__init__.py
wiggelen/commands.py
wiggelen/distance.py
wiggelen/index.py
wiggelen/intervals.py
wiggelen/merge.py
wiggelen/parse.py
wiggelen/plot.py
wiggelen/transform.py
wiggelen/wiggle.py
wiggelen.egg-info/PKG-INFO
wiggelen.egg-info/SOURCES.txt
wiggelen.egg-info/dependency_links.txt
wiggelen.egg-info/entry_points.txt
wiggelen.egg-info/top_level.txt