Metadata-Version: 1.1
Name: wiggelen
Version: 0.2.0
Summary: Working with wiggle tracks in Python
Home-page: https://github.com/martijnvermaat/wiggelen
Author: LUMC, Martijn Vermaat, Jeroen Laros
Author-email: m.vermaat.hg@lumc.nl
License: MIT License
Keywords: bioinformatics
Platform: any
Classifier: Development Status :: 3 - Alpha
Classifier: Intended Audience :: Developers
Classifier: Intended Audience :: Science/Research
Classifier: Operating System :: OS Independent
Classifier: Programming Language :: Python
Classifier: Topic :: Scientific/Engineering
